{"name":"build-javascript","namedChunkGroups":{"polyfill":{"name":"polyfill","assets":[{"name":"webpack-runtime-489895f99e4f39789ac3.js","size":5142},{"name":"polyfill-07f51bf77b2ed9c13035.js","size":85027}],"filteredAssets":0,"assetsSize":90169,"filteredAuxiliaryAssets":2,"auxiliaryAssetsSize":231278},"app":{"name":"app","assets":[{"name":"webpack-runtime-489895f99e4f39789ac3.js","size":5142},{"name":"framework-038630bf0e7a97d5fb45.js","size":205460},{"name":"app-f2a94c91ec8316a4558b.js","size":115035}],"filteredAssets":0,"assetsSize":325637,"filteredAuxiliaryAssets":3,"auxiliaryAssetsSize":971371},"component---src-pages-404-js":{"name":"component---src-pages-404-js","assets":[{"name":"styles.5705086efdd0b9eb20e4.css","size":6470},{"name":"1bfc9850-96b371b69ddb2b0a5629.js","size":711},{"name":"component---src-pages-404-js-acfec5fa271ea0f5ee93.js","size":3371}],"filteredAssets":0,"assetsSize":10552,"filteredAuxiliaryAssets":3,"auxiliaryAssetsSize":1624687},"component---src-pages-about-js":{"name":"component---src-pages-about-js","assets":[{"name":"styles.5705086efdd0b9eb20e4.css","size":6470},{"name":"1bfc9850-96b371b69ddb2b0a5629.js","size":711},{"name":"component---src-pages-about-js-0fd4ee6acfb42d159494.js","size":3303}],"filteredAssets":0,"assetsSize":10484,"filteredAuxiliaryAssets":3,"auxiliaryAssetsSize":1624602},"component---src-pages-contact-js":{"name":"component---src-pages-contact-js","assets":[{"name":"styles.5705086efdd0b9eb20e4.css","size":6470},{"name":"1bfc9850-96b371b69ddb2b0a5629.js","size":711},{"name":"component---src-pages-contact-js-38b20f6a89123aad5401.js","size":4384}],"filteredAssets":0,"assetsSize":11565,"filteredAuxiliaryAssets":3,"auxiliaryAssetsSize":1626663},"component---src-pages-index-js":{"name":"component---src-pages-index-js","assets":[{"name":"styles.5705086efdd0b9eb20e4.css","size":6470},{"name":"1bfc9850-96b371b69ddb2b0a5629.js","size":711},{"name":"component---src-pages-index-js-102d89a6bccff8d6df0a.js","size":13883}],"filteredAssets":0,"assetsSize":21064,"filteredAuxiliaryAssets":3,"auxiliaryAssetsSize":1690992}},"assetsByChunkName":{"polyfill":["webpack-runtime-489895f99e4f39789ac3.js","polyfill-07f51bf77b2ed9c13035.js"],"app":["webpack-runtime-489895f99e4f39789ac3.js","framework-038630bf0e7a97d5fb45.js","app-f2a94c91ec8316a4558b.js"],"component---src-pages-404-js":["styles.5705086efdd0b9eb20e4.css","1bfc9850-96b371b69ddb2b0a5629.js","component---src-pages-404-js-acfec5fa271ea0f5ee93.js"],"component---src-pages-about-js":["styles.5705086efdd0b9eb20e4.css","1bfc9850-96b371b69ddb2b0a5629.js","component---src-pages-about-js-0fd4ee6acfb42d159494.js"],"component---src-pages-contact-js":["styles.5705086efdd0b9eb20e4.css","1bfc9850-96b371b69ddb2b0a5629.js","component---src-pages-contact-js-38b20f6a89123aad5401.js"],"component---src-pages-index-js":["styles.5705086efdd0b9eb20e4.css","1bfc9850-96b371b69ddb2b0a5629.js","component---src-pages-index-js-102d89a6bccff8d6df0a.js"]},"childAssetsByChunkName":{}}